LICENSE
MANIFEST.in
README.rst
setup.py
Flask_MongoMyAdmin.egg-info/PKG-INFO
Flask_MongoMyAdmin.egg-info/SOURCES.txt
Flask_MongoMyAdmin.egg-info/dependency_links.txt
Flask_MongoMyAdmin.egg-info/not-zip-safe
Flask_MongoMyAdmin.egg-info/requires.txt
Flask_MongoMyAdmin.egg-info/top_level.txt
flask_mongomyadmin/__init__.py
flask_mongomyadmin/admin.py
flask_mongomyadmin/static/mongomyadmin/bootstrap/css/bootstrap-responsive.css
flask_mongomyadmin/static/mongomyadmin/bootstrap/css/bootstrap-responsive.min.css
flask_mongomyadmin/static/mongomyadmin/bootstrap/css/bootstrap.css
flask_mongomyadmin/static/mongomyadmin/bootstrap/css/bootstrap.min.css
flask_mongomyadmin/static/mongomyadmin/bootstrap/img/glyphicons-halflings-white.png
flask_mongomyadmin/static/mongomyadmin/bootstrap/img/glyphicons-halflings.png
flask_mongomyadmin/static/mongomyadmin/bootstrap/js/bootstrap.js
flask_mongomyadmin/static/mongomyadmin/bootstrap/js/bootstrap.min.js
flask_mongomyadmin/templates/mongomyadmin/choose_collection.html
flask_mongomyadmin/templates/mongomyadmin/choose_database.html
flask_mongomyadmin/templates/mongomyadmin/collection_header.html
flask_mongomyadmin/templates/mongomyadmin/db_chooser.html
flask_mongomyadmin/templates/mongomyadmin/footer.html
flask_mongomyadmin/templates/mongomyadmin/header.html
flask_mongomyadmin/templates/mongomyadmin/mongo_document.html
flask_mongomyadmin/templates/mongomyadmin/new_document.html
flask_mongomyadmin/templates/mongomyadmin/pager.html
flask_mongomyadmin/templates/mongomyadmin/search_collection.html