Metadata-Version: 1.1
Name: Flask-MongoMyAdmin
Version: 0.1
Summary: Simple MongoDB Administrative Interface for Flask
Home-page: http://github.com/classicspecs/Flask-MongoMyAdmin/
Author: Jay Goel
Author-email: jay@classicspecs.com
License: UNKNOWN
Platform: any
Classifier: Environment :: Web Environment
Classifier: Intended Audience :: Developers
Classifier: License :: OSI Approved :: Apache Software License
Classifier: Operating System :: OS Independent
Classifier: Programming Language :: Python
Classifier: Topic :: Internet :: WWW/HTTP :: Dynamic Content
Classifier: Topic :: Software Development :: Libraries :: Python Modules
